.coveragerc
.gitignore
.gitmodules
CHANGES.txt
README.rst
demo.ini
setup.cfg
setup.py
tox.ini
deform_bootstrap/__init__.py
deform_bootstrap/resources.py
deform_bootstrap/utils.py
deform_bootstrap/widget.py
deform_bootstrap.egg-info/PKG-INFO
deform_bootstrap.egg-info/SOURCES.txt
deform_bootstrap.egg-info/dependency_links.txt
deform_bootstrap.egg-info/not-zip-safe
deform_bootstrap.egg-info/requires.txt
deform_bootstrap.egg-info/top_level.txt
deform_bootstrap/demo/__init__.py
deform_bootstrap/demo/main.pt
deform_bootstrap/demo/test.py
deform_bootstrap/demo/test_chosen.py
deform_bootstrap/demo/test_dateinput.py
deform_bootstrap/demo/test_typeahead.py
deform_bootstrap/static/bootstrap-datepicker.css
deform_bootstrap/static/bootstrap-datepicker.js
deform_bootstrap/static/bootstrap-datepicker.less
deform_bootstrap/static/bootstrap-typeahead.js
deform_bootstrap/static/bootstrap.min.js
deform_bootstrap/static/chosen_bootstrap.css
deform_bootstrap/static/datepicker.less
deform_bootstrap/static/deform_bootstrap.css
deform_bootstrap/static/deform_bootstrap.js
deform_bootstrap/static/deform_bootstrap.less
deform_bootstrap/static/jquery-1.7.1.min.js
deform_bootstrap/static/jquery-ui-1.8.18.custom.min.js
deform_bootstrap/static/jquery-ui-timepicker-addon-0.9.9.js
deform_bootstrap/static/jquery.form-2.96.js
deform_bootstrap/static/jquery.maskedinput-1.3.js
deform_bootstrap/static/twitter_bootstrap
deform_bootstrap/static/img/glyphicons-halflings-white.png
deform_bootstrap/static/img/glyphicons-halflings.png
deform_bootstrap/static/jquery_chosen/chosen-sprite.png
deform_bootstrap/static/jquery_chosen/chosen.css
deform_bootstrap/static/jquery_chosen/chosen.jquery.js
deform_bootstrap/static/jquery_chosen/chosen.jquery.min.js
deform_bootstrap/templates/checkbox_choice.pt
deform_bootstrap/templates/checked_input.pt
deform_bootstrap/templates/checked_password.pt
deform_bootstrap/templates/chosen_multiple.pt
deform_bootstrap/templates/chosen_optgroup.pt
deform_bootstrap/templates/chosen_single.pt
deform_bootstrap/templates/dateparts.pt
deform_bootstrap/templates/form.pt
deform_bootstrap/templates/mapping.pt
deform_bootstrap/templates/mapping_item.pt
deform_bootstrap/templates/radio_choice.pt
