Metadata-Version: 1.1
Name: deform-bootstrap
Version: 0.2.9
Summary: Twitter Bootstrap compatible widgets, templates and styles for the deform form library
Home-page: https://github.com/Kotti/deform_bootstrap
Author: Daniel Nouri and contributors
Author-email: pylons-discuss@googlegroups.com
License: BSD-derived (http://www.repoze.org/LICENSE.txt)
Keywords: twitter bootstrap deform styles css web forms form
Platform: UNKNOWN
Classifier: Intended Audience :: Developers
Classifier: Programming Language :: Python
